<?xml version="1.0" encoding="UTF-8"?><extraction><clueid>366830779</clueid><fullpath><![CDATA[http://weibo.com/p/100808e12d03f0beb267a9b13c997731c41cb6?pids=Pl_Third_App__11&current_page=39&since_id=%7B%22last_since_id%22%3A3842807426984999%2C%22res_type%22%3A1%2C%22next_since_id%22%3A3842716385840193%7D&page=14#Pl_Third_App__11]]></fullpath><realpath><![CDATA[http://weibo.com/p/100808e12d03f0beb267a9b13c997731c41cb6?current_page=39&since_id={%22last_since_id%22%3A3842807426984999%2C%22res_type%22%3A1%2C%22next_since_id%22%3A3842716385840193}&page=14#Pl_Third_App__11]]></realpath><theme>微博话题采集</theme><middle>default</middle><createdate>2017-5-13 16:1:25</createdate><pageno>13</pageno><actionno></actionno><actionvalue></actionvalue><prestamp>DSEngine-+-ds_browser_ds_task_xp2-+-13803688</prestamp><currentstamp>DSEngine-+-ds_browser_ds_task_xp2-+-13866928</currentstamp><baseURI><bucketBaseURI><bucketName>微博话题</bucketName><uri><![CDATA[http://weibo.com/p/100808e12d03f0beb267a9b13c997731c41cb6?current_page=39&since_id={%22last_since_id%22%3A3842807426984999%2C%22res_type%22%3A1%2C%22next_since_id%22%3A3842716385840193}&page=14#Pl_Third_App__11]]></uri></bucketBaseURI></baseURI>
<微博话题><item><话题>#全国防灾减灾日#</话题><导语>
				导语：2008年5月12日14时28分04秒，四川汶川、北川发生里氏8.0级地震，地震造成69227人遇难，374643人受伤，17923人失踪。此次地震为新中国成立以来国内破坏性最强、波及范围最广、总伤亡人数最多的一次地震。自09年起，5月12日为全国防灾减灾日。
			</导语><阅读数>4571.6万</阅读数><讨论数>3万</讨论数><粉丝数>89</粉丝数><列><item><样例><item><博主>科普中国</博主><博主id>5104880035</博主id><博主主页>http://weibo.com/kepuzhongguo?refer_flag=1008085010_</博主主页><博主头像>http://tva2.sinaimg.cn/crop.62.96.447.447.50/005ztyuLjw8eoa9kjas99j30g30fxt9x.jpg</博主头像><博文>置顶                                                    #全国防灾减灾日# 5·12汶川地震难忘的记忆，你还记得吗？今天是汶川地震8周年纪念日，那场灾难的记忆还未完全抹去，前不久的日本地震又揭开了人们心口的伤疤。有人说，对地震的恐慌来自对地震的不了解。今天还是我国第8个防灾减灾日，防灾甚于救灾，你也许需要知道下地震的真面目！ ​​​​                                            </博文><博文独立网址>http://weibo.com/5104880035/Dva9HxFLd</博文独立网址><发布时间>2016-05-12 11:29</发布时间><发布终端>微博 weibo.com</发布终端><转发数> 149</转发数><评论数> 32</评论数><点赞数>86</点赞数><转发_博主/><转发_博主id/><转发_博主主页/><转发_博文/><转发_发布时间/><转发_发布终端/><转发_转发数/><转发_评论数/><转发_点赞数/><EXPORTFLAG/></item><item><博主>科普中国</博主><博主id>5104880035</博主id><博主主页>http://weibo.com/kepuzhongguo?refer_flag=1008085010_</博主主页><博主头像>http://tva2.sinaimg.cn/crop.62.96.447.447.50/005ztyuLjw8eoa9kjas99j30g30fxt9x.jpg</博主头像><博文>置顶                                                    #全国防灾减灾日# 夏季是各种灾害的频发季节，暴雨、粉尘爆炸、沉船、泥石流……灾难一旦发生，就会造成人员伤亡，如果自救知识储备多一点，也许受到的伤害也会少一点。万一我们遇上了这样的灾难事件应该怎么办？今天，我们就来普及一下日常灾难的自救方法…… ​​​​                                            </博文><博文独立网址>http://weibo.com/5104880035/DuZnRpQSR</博文独立网址><发布时间>2016-05-11 08:04</发布时间><发布终端>微博 weibo.com</发布终端><转发数> 164</转发数><评论数> 28</评论数><点赞数>19</点赞数><转发_博主/><转发_博主id/><转发_博主主页/><转发_博文/><转发_发布时间/><转发_发布终端/><转发_转发数/><转发_评论数/><转发_点赞数/><EXPORTFLAG/></item><item><博主>福建水电学院团委</博主><博主id>2538499704</博主id><博主主页>http://weibo.com/fjsdxytw?refer_flag=1008085010_</博主主页><博主头像>http://tva1.sinaimg.cn/crop.0.0.417.417.50/974e6e78gw1eo7vktazdsj20bm0bmq5q.jpg</博主头像><博文>置顶                                                    #全国防灾减灾日#【逃生自救攻略】作为一名学生，不仅在校内要注意防灾减灾，在外也要时刻警惕一些潜在的灾害因素，因此提高我们的防灾减灾意识非常重要。快戳底下大图学习学习吧@共青团中央 @共青团福建省委 @中国大学生在线 ​​​​                                            </博文><博文独立网址>http://weibo.com/2538499704/ChrPhcyS2</博文独立网址><发布时间>2015-05-12 08:00</发布时间><发布终端>微博 weibo.com</发布终端><转发数> 35</转发数><评论数> 3</评论数><点赞数>9</点赞数><转发_博主/><转发_博主id/><转发_博主主页/><转发_博文/><转发_发布时间/><转发_发布终端/><转发_转发数/><转发_评论数/><转发_点赞数/><EXPORTFLAG/></item></样例></item><item><样例><item><博主>飞雪肖成</博主><博主id>2621317403</博主id><博主主页>http://weibo.com/u/2621317403?refer_flag=1008085010_</博主主页><博主头像>http://tva4.sinaimg.cn/crop.0.0.540.540.50/9c3e211bjw8eizdsefb9zj20f00f0757.jpg</博主头像><博文>                                                    //@庐陵老狼:普及防灾知识,增强减灾意识                                            </博文><博文独立网址>http://weibo.com/2621317403/ChGpb4yHC</博文独立网址><发布时间>2015-05-13 21:06</发布时间><发布终端>三星GALAXY S4</发布终端><转发数>转发</转发数><评论数>评论</评论数><点赞数>2</点赞数><转发_博主>吉安爱心会2012</转发_博主><转发_博主id>2478331101</转发_博主id><转发_博主主页>http://weibo.com/u/2478331101?refer_flag=1008085010_</转发_博主主页><转发_博文>
                                    #全国防灾减灾日# 吉安爱心会、 @共青团吉安市吉州区委、吉安麦田、吉安兰天救援队5月12日上午在吉州区思源学校开展防灾救援演练活动顺利结束。@壹基金救灾 @减灾小课堂 @陕西妇源汇 @井冈山报 @吉安晚报 @吉安晨报V @共青团吉安市宣传 @吉安发布 @庐陵城事 @益路阳光公益 @飞雪肖成 @庐陵老狼 ​​​​
                                                                </转发_博文><转发_发布时间>2015-5-12 13:10</转发_发布时间><转发_发布终端>360安全浏览器</转发_发布终端><转发_转发数>转发 3</转发_转发数><转发_评论数>评论 1</转发_评论数><转发_点赞数> 4</转发_点赞数><EXPORTFLAG/></item><item><博主>安顺车辆管理所</博主><博主id>2662083433</博主id><博主主页>http://weibo.com/ascgs?refer_flag=1008085010_</博主主页><博主头像>http://tva4.sinaimg.cn/crop.0.0.180.180.50/9eac2b69jw1e8qgp5bmzyj2050050aa8.jpg</博主头像><博文>                                                    转发微博                                            </博文><博文独立网址>http://weibo.com/2662083433/ChURLlAxG</博文独立网址><发布时间>2015-05-15 09:55</发布时间><发布终端>微博 weibo.com</发布终端><转发数>转发</转发数><评论数>评论</评论数><点赞数>赞</点赞数><转发_博主>公安部打四黑除四害</转发_博主><转发_博主id>2328516855</转发_博主id><转发_博主主页>http://weibo.com/dshcsh?refer_flag=1008085010_</转发_博主主页><转发_博文>
                                    【全国防灾减灾日，这些防灾常识你必须掌握！】地震、火灾、洪水、台风、泥石流……灾难总是不期而至，及早掌握防灾自救技能非常重要！遭遇地震如何躲避？洪水、火灾如何逃生？发现有人煤气中毒、触电怎么施救……今天，#全国防灾减灾日#，一起学习防灾常识，关键时刻能救命！扩散！ ​​​​
                                                                </转发_博文><转发_发布时间>2015-5-12 09:20</转发_发布时间><转发_发布终端>Android</转发_发布终端><转发_转发数>转发 768</转发_转发数><转发_评论数>评论 51</转发_评论数><转发_点赞数> 61</转发_点赞数><EXPORTFLAG/></item><item><博主>兴隽净水</博主><博主id>2749655262</博主id><博主主页>http://weibo.com/u/2749655262?refer_flag=1008085010_</博主主页><博主头像>http://tva1.sinaimg.cn/crop.0.8.384.384.50/a3e468degw1eidia745lkj20aq0bbmy1.jpg</博主头像><博文>                                                    转发微博                                            </博文><博文独立网址>http://weibo.com/2749655262/Chsoky9PE</博文独立网址><发布时间>2015-05-12 09:26</发布时间><发布终端>微博 weibo.com</发布终端><转发数>转发</转发数><评论数>评论</评论数><点赞数>1</点赞数><转发_博主>扬子晚报</转发_博主><转发_博主id>1653603955</转发_博主id><转发_博主主页>http://weibo.com/yangtse?refer_flag=1008085010_</转发_博主主页><转发_博文>
                                    【全国防灾减灾日，你必须掌握的防灾常识！】地震、火灾、洪水、台风、泥石流……当遇到这些自然灾害，你真的知道如何正确躲避吗？今天#全国防灾减灾日#，戳图↓↓学习防灾常识，转起收藏，关键时刻能救命！（人民网） ​​​​
                                                                </转发_博文><转发_发布时间>2015-5-12 09:24</转发_发布时间><转发_发布终端>微博 weibo.com</转发_发布终端><转发_转发数>转发 86</转发_转发数><转发_评论数>评论 7</转发_评论数><转发_点赞数> 22</转发_点赞数><EXPORTFLAG/></item><item><博主>智农网络</博主><博主id>5429604774</博主id><博主主页>http://weibo.com/zhinongwangluo?refer_flag=1008085010_</博主主页><博主头像>http://tva1.sinaimg.cn/crop.0.1.1242.1242.50/005Vs4eyjw8eo5pi0y7atj30yi0ykgol.jpg</博主头像><博文>                                                    小智响应@中国气象局 号召，承接合肥市政府气象科普购买服务，将会举办更多气象科普活动，真正让气象科普服务社会化！//@安徽农网程者农夫:及时响应@中国气象局 号召，安徽@智农网络 承接合肥市政府气象科普购买服务。已多次举办气象科普活动，真正让气象科普服务社会化！                                            </博文><博文独立网址>http://weibo.com/5429604774/ChUKnBo6B</博文独立网址><发布时间>2015-05-15 09:37</发布时间><发布终端>iPhone 6 Plus</发布终端><转发数> 1</转发数><评论数>评论</评论数><点赞数>1</点赞数><转发_博主>中国气象科普网</转发_博主><转发_博主id>3194920592</转发_博主id><转发_博主主页>http://weibo.com/u/3194920592?refer_flag=1008085010_</转发_博主主页><转发_博文>
                                    #全国防灾减灾日#今早，咱们的小伙伴们走进合肥市望湖社区开展“防灾减灾日”科普宣传活动通过摆放展板、发放宣传材料、现场咨询等形式，为市民群众献上了安全知识“大餐”。看，还来了许多志愿者～下午走进合肥48中开展“防灾减灾日”气象科普知识讲座，增强师生防灾减灾安全意识。 ​​​​
                                                                </转发_博文><转发_发布时间>2015-5-12 16:51</转发_发布时间><转发_发布终端>微博 weibo.com</转发_发布终端><转发_转发数>转发 24</转发_转发数><转发_评论数>评论 13</转发_评论数><转发_点赞数> 14</转发_点赞数><EXPORTFLAG/></item><item><博主>西华师范大学管理学院两委会</博主><博主id>2833750902</博主id><博主主页>http://weibo.com/xhsfdxglxy?refer_flag=1008085010_</博主主页><博主头像>http://tva1.sinaimg.cn/crop.0.0.166.166.50/a8e79b76gw1emt4b92drwj204n04o0sq.jpg</博主头像><博文>                                                    没有了生命变没有了一切，请珍爱生命                                            </博文><博文独立网址>http://weibo.com/2833750902/ChrtpuZua</博文独立网址><发布时间>2015-05-12 07:06</发布时间><发布终端>手机微博触屏版</发布终端><转发数>转发</转发数><评论数>评论</评论数><点赞数>3</点赞数><转发_博主>人民网</转发_博主><转发_博主id>2286908003</转发_博主id><转发_博主主页>http://weibo.com/renminwang?refer_flag=1008085010_</转发_博主主页><转发_博文>
                                    【全国防灾减灾日，你必须掌握的防灾常识！】地震、火灾、洪水、台风、泥石流……当遇到这些自然灾害，你真的知道如何正确躲避吗？今天#全国防灾减灾日#，戳图↓↓学习防灾常识，转起收藏，关键时刻能救命！ ​​​​
                                                                </转发_博文><转发_发布时间>2015-5-12 07:00</转发_发布时间><转发_发布终端>人民网微博</转发_发布终端><转发_转发数>转发 899</转发_转发数><转发_评论数>评论 87</转发_评论数><转发_点赞数> 168</转发_点赞数><EXPORTFLAG/></item><item><博主>站在风景背后</博主><博主id>2248290410</博主id><博主主页>http://weibo.com/u/2248290410?refer_flag=1008085010_</博主主页><博主头像>http://tva3.sinaimg.cn/crop.0.0.180.180.50/8602306ajw1e8qgp5bmzyj2050050aa8.jpg</博主头像><博文>                                                    转发微博                                            </博文><博文独立网址>http://weibo.com/2248290410/ChUFK7J9I</博文独立网址><发布时间>2015-05-15 09:26</发布时间><发布终端>iPhone 6</发布终端><转发数>转发</转发数><评论数>评论</评论数><点赞数>赞</点赞数><转发_博主>园区斜塘派出所</转发_博主><转发_博主id>1995376251</转发_博主id><转发_博主主页>http://weibo.com/u/1995376251?refer_flag=1008085010_</转发_博主主页><转发_博文>
                                    【全国防灾减灾日，这些防灾常识你必须掌握！】地震、火灾、洪水、台风、泥石流……灾难总是不期而至，及早掌握防灾自救技能非常重要！遭遇地震如何躲避？洪水、火灾如何逃生？发现有人煤气中毒、触电怎么施救……今天，#全国防灾减灾日#，一起学习防灾常识，关键时刻能救命！扩散！ ​​​​
                                                                </转发_博文><转发_发布时间>2015-5-12 10:39</转发_发布时间><转发_发布终端>360安全浏览器</转发_发布终端><转发_转发数>转发 5</转发_转发数><转发_评论数>评论</转发_评论数><转发_点赞数> 1</转发_点赞数><EXPORTFLAG/></item><item><博主>心态放的很平</博主><博主id>2306053535</博主id><博主主页>http://weibo.com/u/2306053535?refer_flag=1008085010_</博主主页><博主头像>http://tva4.sinaimg.cn/crop.0.0.290.290.50/8973959fjw8ec9th4d6yuj20820820sv.jpg</博主头像><博文>                                                    转发微博                                            </博文><博文独立网址>http://weibo.com/2306053535/ChEOK0nsu</博文独立网址><发布时间>2015-05-13 17:04</发布时间><发布终端>微博 weibo.com</发布终端><转发数>转发</转发数><评论数> 1</评论数><点赞数>赞</点赞数><转发_博主>大众汽车蓝创未来</转发_博主><转发_博主id>3065085677</转发_博主id><转发_博主主页>http://weibo.com/vwthinkblue?refer_flag=1008085010_</转发_博主主页><转发_博文>
                                    #蓝色冷知识#古人云，天灾人祸在所难免。但随着人类对于地球的污染，很多灾难并非“天注定”。今天，是第7个#全国防灾减灾日#，让我们一起来反思那些因污染而起的“天灾”吧！ ​​​​
                                                                </转发_博文><转发_发布时间>2015-5-12 11:55</转发_发布时间><转发_发布终端>微博 weibo.com</转发_发布终端><转发_转发数>转发 495</转发_转发数><转发_评论数>评论 341</转发_评论数><转发_点赞数> 22</转发_点赞数><EXPORTFLAG/></item><item><博主>安阳市第二十五中学</博主><博主id>5118926577</博主id><博主主页>http://weibo.com/u/5118926577?refer_flag=1008085010_</博主主页><博主头像>http://tva3.sinaimg.cn/crop.102.2.1842.1842.50/005AquDTjw1emxjxtafk2j31kw1fk4fm.jpg</博主头像><博文>                                                    【今天是#全国防灾减灾日#，你必须掌握的防灾常识！】地震、火灾、洪水、台风、泥石流……当遇到这些自然灾害，你真的知道如何正确躲避吗？戳图↓↓学习防灾常识，转起收藏，关键时刻能救命！                                            </博文><博文独立网址>http://weibo.com/5118926577/Chsunho5M</博文独立网址><发布时间>2015-05-12 09:41</发布时间><发布终端>Android客户端</发布终端><转发数>转发</转发数><评论数> 1</评论数><点赞数>12</点赞数><转发_博主>安阳市教育局</转发_博主><转发_博主id>3052564797</转发_博主id><转发_博主主页>http://weibo.com/u/3052564797?refer_flag=1008085010_</转发_博主主页><转发_博文>
                                    【今天是#全国防灾减灾日#，你必须掌握的防灾常识！】地震、火灾、洪水、台风、泥石流……当遇到这些自然灾害，你真的知道如何正确躲避吗？戳图↓↓学习防灾常识，转起收藏，关键时刻能救命！ ​​​​
                                                                </转发_博文><转发_发布时间>2015-5-12 08:09</转发_发布时间><转发_发布终端>微博桌面</转发_发布终端><转发_转发数>转发 21</转发_转发数><转发_评论数>评论 5</转发_评论数><转发_点赞数> 7</转发_点赞数><EXPORTFLAG/></item><item><博主>郑轻科学校区园区团工委</博主><博主id>2680467273</博主id><博主主页>http://weibo.com/u/2680467273?refer_flag=1008085010_</博主主页><博主头像>http://tva3.sinaimg.cn/crop.0.0.180.180.50/9fc4af49jw1e8qgp5bmzyj2050050aa8.jpg</博主头像><博文>                                                    好快。一过就是七年。5月12号汶川地震。                                            </博文><博文独立网址>http://weibo.com/2680467273/ChtDO6Jld</博文独立网址><发布时间>2015-05-12 12:37</发布时间><发布终端>荣耀6</发布终端><转发数> 1</转发数><评论数>评论</评论数><点赞数>1</点赞数><转发_博主>人民网</转发_博主><转发_博主id>2286908003</转发_博主id><转发_博主主页>http://weibo.com/renminwang?refer_flag=1008085010_</转发_博主主页><转发_博文>
                                    【全国防灾减灾日，你必须掌握的防灾常识！】地震、火灾、洪水、台风、泥石流……当遇到这些自然灾害，你真的知道如何正确躲避吗？今天#全国防灾减灾日#，戳图↓↓学习防灾常识，转起收藏，关键时刻能救命！ ​​​​
                                                                </转发_博文><转发_发布时间>2015-5-12 07:00</转发_发布时间><转发_发布终端>人民网微博</转发_发布终端><转发_转发数>转发 899</转发_转发数><转发_评论数>评论 87</转发_评论数><转发_点赞数> 168</转发_点赞数><EXPORTFLAG/></item><item><博主>吉林舒兰吉舒派出所2013</博主><博主id>3286238653</博主id><博主主页>http://weibo.com/u/3286238653?refer_flag=1008085010_</博主主页><博主头像>http://tva2.sinaimg.cn/crop.0.0.180.180.50/c3e005bdjw1e8qgp5bmzyj2050050aa8.jpg</博主头像><博文>                                                    //@吉林市公安局: 转发微博                                            </博文><博文独立网址>http://weibo.com/3286238653/ChUwBj0Rb</博文独立网址><发布时间>2015-05-15 09:03</发布时间><发布终端>微博 weibo.com</发布终端><转发数>转发</转发数><评论数>评论</评论数><点赞数>赞</点赞数><转发_博主>公安部打四黑除四害</转发_博主><转发_博主id>2328516855</转发_博主id><转发_博主主页>http://weibo.com/dshcsh?refer_flag=1008085010_</转发_博主主页><转发_博文>
                                    【全国防灾减灾日，这些防灾常识你必须掌握！】地震、火灾、洪水、台风、泥石流……灾难总是不期而至，及早掌握防灾自救技能非常重要！遭遇地震如何躲避？洪水、火灾如何逃生？发现有人煤气中毒、触电怎么施救……今天，#全国防灾减灾日#，一起学习防灾常识，关键时刻能救命！扩散！ ​​​​
                                                                </转发_博文><转发_发布时间>2015-5-12 09:20</转发_发布时间><转发_发布终端>Android</转发_发布终端><转发_转发数>转发 768</转发_转发数><转发_评论数>评论 51</转发_评论数><转发_点赞数> 61</转发_点赞数><EXPORTFLAG/></item><item><博主>洋浦消防支队</博主><博主id>5460918630</博主id><博主主页>http://weibo.com/yangpu119?refer_flag=1008085010_</博主主页><博主头像>http://tva4.sinaimg.cn/crop.81.22.266.266.50/005XzsoKgw1evf1c5atfij30cc08ojsa.jpg</博主头像><博文>                                                    #全国防灾减灾日# 【关于防灾减灾 你不知道的1:7】也许你经常担心自己孩子的安全，也许你有对孩子进行安全教育。但是，作为家长的你，真的具备较强的防灾意识吗？↓↓↓下面这项调查显示，大多数国人的防灾减灾意识和知识仍较为欠缺。你也是其中之一！ ​​​​                                            </博文><博文独立网址>http://weibo.com/5460918630/ChUv3jde6</博文独立网址><发布时间>2015-05-15 08:59</发布时间><发布终端>iPhone 6</发布终端><转发数>转发</转发数><评论数>评论</评论数><点赞数>赞</点赞数><转发_博主/><转发_博主id/><转发_博主主页/><转发_博文/><转发_发布时间/><转发_发布终端/><转发_转发数/><转发_评论数/><转发_点赞数/><EXPORTFLAG/></item><item><博主>吉林市公安局户政管理支队</博主><博主id>2975898663</博主id><博主主页>http://weibo.com/u/2975898663?refer_flag=1008085010_</博主主页><博主头像>http://tva4.sinaimg.cn/crop.0.0.180.180.50/b1609c27jw1e8qgp5bmzyj2050050aa8.jpg</博主头像><博文>                                                    转发微博                                            </博文><博文独立网址>http://weibo.com/2975898663/ChUs1llds</博文独立网址><发布时间>2015-05-15 08:52</发布时间><发布终端>微博 weibo.com</发布终端><转发数>转发</转发数><评论数>评论</评论数><点赞数>赞</点赞数><转发_博主>公安部打四黑除四害</转发_博主><转发_博主id>2328516855</转发_博主id><转发_博主主页>http://weibo.com/dshcsh?refer_flag=1008085010_</转发_博主主页><转发_博文>
                                    【全国防灾减灾日，这些防灾常识你必须掌握！】地震、火灾、洪水、台风、泥石流……灾难总是不期而至，及早掌握防灾自救技能非常重要！遭遇地震如何躲避？洪水、火灾如何逃生？发现有人煤气中毒、触电怎么施救……今天，#全国防灾减灾日#，一起学习防灾常识，关键时刻能救命！扩散！ ​​​​
                                                                </转发_博文><转发_发布时间>2015-5-12 09:20</转发_发布时间><转发_发布终端>Android</转发_发布终端><转发_转发数>转发 768</转发_转发数><转发_评论数>评论 51</转发_评论数><转发_点赞数> 61</转发_点赞数><EXPORTFLAG/></item><item><博主>萤萤AH</博主><博主id>2199465261</博主id><博主主页>http://weibo.com/u/2199465261?refer_flag=1008085010_</博主主页><博主头像>http://tva3.sinaimg.cn/crop.0.0.180.180.50/83192d2djw1e8qgp5bmzyj2050050aa8.jpg</博主头像><博文>                                                    转发微博                                            </博文><博文独立网址>http://weibo.com/2199465261/ChUn966JU</博文独立网址><发布时间>2015-05-15 08:40</发布时间><发布终端>红米手机</发布终端><转发数>转发</转发数><评论数>评论</评论数><点赞数>赞</点赞数><转发_博主>南国都市报</转发_博主><转发_博主id>1962117985</转发_博主id><转发_博主主页>http://weibo.com/ngdsb2011?refer_flag=1008085010_</转发_博主主页><转发_博文>
                                    【图解：发生地震 在海口的你往哪躲？】如果海口发生地震，咱们往哪跑能逃生？万绿园啊！拜托，海南人都知道，但为啥不见应急设施？都在草坪底下呢~掀起来就能搭帐篷啦！还有23个用水点、8处应急厕所和5处移动厕所，可满足4.6万人需求。今天是#全国防灾减灾日#，这些你一定要懂↓O图解第50期：发生地震海口市民该怎么做？南海... ​​​​
                                                                </转发_博文><转发_发布时间>2015-5-12 17:17</转发_发布时间><转发_发布终端>iPhone客户端</转发_发布终端><转发_转发数>转发 9</转发_转发数><转发_评论数>评论 3</转发_评论数><转发_点赞数> 4</转发_点赞数><EXPORTFLAG/></item><item><博主>防灾科技学院大学生救援队</博主><博主id>5121442118</博主id><博主主页>http://weibo.com/CIDPVSAR?refer_flag=1008085010_</博主主页><博主头像>http://tva3.sinaimg.cn/crop.124.17.408.408.50/005AB338jw1en1bgq05brj30iw0dcdhj.jpg</博主头像><博文>                                                    5·12疏散演练 幕后工作 #全国防灾减灾日##疏散演练##512# ​​​​                                            </博文><博文独立网址>http://weibo.com/5121442118/ChxLya8ZT</博文独立网址><发布时间>2015-05-12 23:07</发布时间><发布终端>iPhone客户端</发布终端><转发数> 9</转发数><评论数> 5</评论数><点赞数>11</点赞数><转发_博主/><转发_博主id/><转发_博主主页/><转发_博文/><转发_发布时间/><转发_发布终端/><转发_转发数/><转发_评论数/><转发_点赞数/><EXPORTFLAG/></item><item><博主>姚小米的菜</博主><博主id>2526541924</博主id><博主主页>http://weibo.com/u/2526541924?refer_flag=1008085010_</博主主页><博主头像>http://tva4.sinaimg.cn/crop.0.0.748.748.50/9697f864jw8egzo7mat3xj20ks0ks767.jpg</博主头像><博文>                                                    转发微博                                            </博文><博文独立网址>http://weibo.com/2526541924/ChsWK1SgY</博文独立网址><发布时间>2015-05-12 10:51</发布时间><发布终端>Android客户端</发布终端><转发数>转发</转发数><评论数>评论</评论数><点赞数>1</点赞数><转发_博主>扬子晚报</转发_博主><转发_博主id>1653603955</转发_博主id><转发_博主主页>http://weibo.com/yangtse?refer_flag=1008085010_</转发_博主主页><转发_博文>
                                    【全国防灾减灾日，你必须掌握的防灾常识！】地震、火灾、洪水、台风、泥石流……当遇到这些自然灾害，你真的知道如何正确躲避吗？今天#全国防灾减灾日#，戳图↓↓学习防灾常识，转起收藏，关键时刻能救命！（人民网） ​​​​
                                                                </转发_博文><转发_发布时间>2015-5-12 09:24</转发_发布时间><转发_发布终端>微博 weibo.com</转发_发布终端><转发_转发数>转发 86</转发_转发数><转发_评论数>评论 7</转发_评论数><转发_点赞数> 22</转发_点赞数><EXPORTFLAG/></item><item><博主>呵呵你一脸鸭汤</博主><博主id>1950094597</博主id><博主主页>http://weibo.com/hswdwb1996929?refer_flag=1008085010_</博主主页><博主头像>http://tva3.sinaimg.cn/crop.0.0.720.720.50/743c1505jw8eth94f9myrj20k00k075x.jpg</博主头像><博文>                                                    //@福建水院数控1431团支部:转发微博                                            </博文><博文独立网址>http://weibo.com/1950094597/ChUalnXwy</博文独立网址><发布时间>2015-05-15 08:08</发布时间><发布终端>vivo智能手机</发布终端><转发数>转发</转发数><评论数>评论</评论数><点赞数>赞</点赞数><转发_博主>福建水电学院团委</转发_博主><转发_博主id>2538499704</转发_博主id><转发_博主主页>http://weibo.com/fjsdxytw?refer_flag=1008085010_</转发_博主主页><转发_博文>
                                    #全国防灾减灾日#【逃生自救攻略】作为一名学生，不仅在校内要注意防灾减灾，在外也要时刻警惕一些潜在的灾害因素，因此提高我们的防灾减灾意识非常重要。快戳底下大图学习学习吧@共青团中央 @共青团福建省委 @中国大学生在线 ​​​​
                                                                </转发_博文><转发_发布时间>2015-5-12 08:00</转发_发布时间><转发_发布终端>微博 weibo.com</转发_发布终端><转发_转发数>转发 35</转发_转发数><转发_评论数>评论 3</转发_评论数><转发_点赞数> 9</转发_点赞数><EXPORTFLAG/></item><item><博主>南平微新闻</博主><博主id>2216651507</博主id><博主主页>http://weibo.com/209292668?refer_flag=1008085010_</博主主页><博主头像>http://tva3.sinaimg.cn/crop.266.129.256.256.50/841f6af3gw1egbt4nehynj20m80goq44.jpg</博主头像><博文>                                                    #全国防灾减灾日# 5.12                                            </博文><博文独立网址>http://weibo.com/2216651507/ChsBhqCSB</博文独立网址><发布时间>2015-05-12 09:58</发布时间><发布终端>微博 weibo.com</发布终端><转发数>转发</转发数><评论数>评论</评论数><点赞数>赞</点赞数><转发_博主>雪_精灵之舞</转发_博主><转发_博主id>2570634750</转发_博主id><转发_博主主页>http://weibo.com/u/2570634750?refer_flag=1008085010_</转发_博主主页><转发_博文>
                                    今天是防灾减灾日的日子～@南平微新闻 @南平那些事 ​​​​
                                                                </转发_博文><转发_发布时间>2015-5-12 09:49</转发_发布时间><转发_发布终端>iPhone 6</转发_发布终端><转发_转发数>转发 1</转发_转发数><转发_评论数>评论 2</转发_评论数><转发_点赞数/><EXPORTFLAG/></item></样例></item></列></item></微博话题></extraction>