<?xml version="1.0" encoding="UTF-8"?><extraction><clueid>367215805</clueid><fullpath><![CDATA[http://s.weibo.com/weibo/%25E9%25AD%258F%25E5%2588%2599%25E8%25A5%25BF%25E4%25BA%258B%25E4%25BB%25B6&typeall=1&suball=1&timescope=custom::2017-05-16-23&page=24]]></fullpath><realpath><![CDATA[http://s.weibo.com/weibo/%25E9%25AD%258F%25E5%2588%2599%25E8%25A5%25BF%25E4%25BA%258B%25E4%25BB%25B6&typeall=1&suball=1&timescope=custom::2017-05-16-23&page=24]]></realpath><theme>微博关键词搜索采集</theme><middle>default</middle><createdate>2017-5-16 21:31:22</createdate><pageno>23</pageno><actionno></actionno><actionvalue></actionvalue><prestamp>DSEngine-+-ds_browser_ds_task_xp1-+-292846509</prestamp><currentstamp>DSEngine-+-ds_browser_ds_task_xp1-+-292863534</currentstamp><baseURI><bucketBaseURI><bucketName>list</bucketName><uri><![CDATA[http://s.weibo.com/weibo/%25E9%25AD%258F%25E5%2588%2599%25E8%25A5%25BF%25E4%25BA%258B%25E4%25BB%25B6&typeall=1&suball=1&timescope=custom::2017-05-16-23&page=24]]></uri></bucketBaseURI></baseURI>
<列表><item><关键字>魏则西事件</关键字><列><item><博主头像>http://tva3.sinaimg.cn/crop.0.0.200.200.50/c0509e07jw1ew5kfzcqhoj205k05kweh.jpg</博主头像><博主id>3226508807</博主id><博主>閑渔翻身</博主><博主主页>http://weibo.com/u/3226508807?refer_flag=1001030103_</博主主页><博文>
		魏则西百度推广事件谁以后再敢说有问题找度娘 我特么就是你干爹。  ​
		</博文><博文独立网址>http://weibo.com/3226508807/ECwzYcCjK?refer_flag=1001030103_</博文独立网址><发布时间>2017-04-01 20:11</发布时间><发布终端>微博 weibo.com</发布终端><转发数/><评论数/><点赞数/><EXPORTFLAG/></item><item><博主头像>http://tva1.sinaimg.cn/crop.0.0.190.190.50/a8f85587jw8f1jlqqhts1j205a05agm4.jpg</博主头像><博主id>2834847111</博主id><博主>东方龙9181</博主><博主主页>http://weibo.com/u/2834847111?refer_flag=1001030103_</博主主页><博文>
		魏则西百度推广事件谁以后再敢说有问题找度娘 我特么就是你干爹。  ​
		</博文><博文独立网址>http://weibo.com/2834847111/ECrWb9vFc?refer_flag=1001030103_</博文独立网址><发布时间>2017-04-01 08:22</发布时间><发布终端>微博 weibo.com</发布终端><转发数>1</转发数><评论数/><点赞数/><EXPORTFLAG/></item><item><博主头像>http://tva3.sinaimg.cn/crop.0.0.150.150.50/5e6b2b4fjw1f4n2adabhvj2046046aa1.jpg</博主头像><博主id>1584081743</博主id><博主>shanshi6600_856</博主><博主主页>http://weibo.com/u/1584081743?refer_flag=1001030103_</博主主页><博文>
		魏则西百度推广事件谁以后再敢说有问题找度娘 我特么就是你干爹。  ​
		</博文><博文独立网址>http://weibo.com/1584081743/ECnVM9RYP?refer_flag=1001030103_</博文独立网址><发布时间>2017-03-31 22:10</发布时间><发布终端>微博 weibo.com</发布终端><转发数/><评论数/><点赞数/><EXPORTFLAG/></item><item><博主头像>http://tvax3.sinaimg.cn/crop.0.0.996.996.50/e2617e00ly8fdtdzmcm9dj20ro0rowgh.jpg</博主头像><博主id>3798040064</博主id><博主>若木m</博主><博主主页>http://weibo.com/u/3798040064?refer_flag=1001030103_</博主主页><博文>
		魏则西事件中，人民日报连续三天共发了6篇相关文章。5.4社会办医别跑偏了5.5民营医院如何有序生长  国家卫计委等调查武警北京总队二院5.6 国家卫计委:严禁医院出租科室 
			...展开全文c
		</博文><博文独立网址>http://weibo.com/3798040064/ECn5nsAUU?refer_flag=1001030103_</博文独立网址><发布时间>2017-03-31 20:00</发布时间><发布终端>Android</发布终端><转发数/><评论数/><点赞数>1</点赞数><EXPORTFLAG/></item><item><博主头像>http://tva3.sinaimg.cn/crop.0.0.640.640.50/005UqKQGjw8et45ik9o2dj30hs0htjsl.jpg</博主头像><博主id>5414515594</博主id><博主>十年生死俩茫茫x_</博主><博主主页>http://weibo.com/u/5414515594?refer_flag=1001030103_</博主主页><博文>
		正在上班，看了魏则西事件，就想到你，然后就控制不了自己的情绪。那个时候的你，是不是心里也是满满希望到狠狠绝望。十年啊，我没去看过你，我甚至不知道你在哪，我没烧纸给过你。因为我无法接受我和你的唯一的对话方式需要通过这些一个人的自言自语来进行 我怎么敢承认我再也见不到你。[第930天] ​
			...展开全文c
		</博文><博文独立网址>http://weibo.com/5414515594/EClDjhDgJ?refer_flag=1001030103_</博文独立网址><发布时间>2017-03-31 16:19</发布时间><发布终端>iPhone 7</发布终端><转发数/><评论数/><点赞数/><EXPORTFLAG/></item><item><博主头像>http://tvax2.sinaimg.cn/default/images/default_avatar_male_50.gif</博主头像><博主id>1603095617</博主id><博主>黑人sdfrew</博主><博主主页>http://weibo.com/u/1603095617?refer_flag=1001030103_</博主主页><博文>
		魏则西百度推广事件谁以后再敢说有问题找度娘 我特么就是你干爹。  ​
		</博文><博文独立网址>http://weibo.com/1603095617/EChrW3EGE?refer_flag=1001030103_</博文独立网址><发布时间>2017-03-31 05:40</发布时间><发布终端>微博 weibo.com</发布终端><转发数/><评论数/><点赞数/><EXPORTFLAG/></item><item><博主头像>http://tva4.sinaimg.cn/crop.0.0.748.748.50/6f3667bdjw8eqlvbjq849j20ks0ksmyn.jpg</博主头像><博主id>1865836477</博主id><博主>L-啦啦啦啦啦</博主><博主主页>http://weibo.com/u/1865836477?refer_flag=1001030103_</博主主页><博文>
		心疼我们老板一分钟… 魏则西事件导致的行业瘫痪耽误了多少正经搞科研的人和单位
		</博文><博文独立网址>http://weibo.com/1380986125/EC8a5usu1?refer_flag=1001030103_</博文独立网址><发布时间>2017-03-30 23:19</发布时间><发布终端>小米Max</发布终端><转发数/><评论数/><点赞数/><EXPORTFLAG/></item><item><博主头像>http://tva3.sinaimg.cn/crop.0.0.200.200.50/006kB98Xjw1f3cymq4u1zj305k05kdft.jpg</博主头像><博主id>5801176999</博主id><博主>兢玫懂</博主><博主主页>http://weibo.com/u/5801176999?refer_flag=1001030103_</博主主页><博文>
		魏则西的事件，真的是挺遗憾。
		</博文><博文独立网址>http://weibo.com/1894383393/ECd0J7W56?refer_flag=1001030103_</博文独立网址><发布时间>2017-03-30 19:31</发布时间><发布终端>秒拍网页版</发布终端><转发数/><评论数/><点赞数/><EXPORTFLAG/></item><item><博主头像>http://tva2.sinaimg.cn/crop.0.0.199.199.50/006zFfpUgw1f8mqbjgo7pj305k05k745.jpg</博主头像><博主id>6023799466</博主id><博主>努瓦寨佣旋等淑淑</博主><博主主页>http://weibo.com/u/6023799466?refer_flag=1001030103_</博主主页><博文>
		魏则西事件让我对百度彻底失去好感了
		</博文><博文独立网址>http://weibo.com/1894383393/ECd0J7W56?refer_flag=1001030103_</博文独立网址><发布时间>2017-03-30 19:23</发布时间><发布终端>秒拍网页版</发布终端><转发数/><评论数/><点赞数/><EXPORTFLAG/></item><item><博主头像>http://tva3.sinaimg.cn/crop.0.0.499.499.50/6b101a5djw1f5e717ply4j20dw0dwjs6.jpg</博主头像><博主id>1796217437</博主id><博主>艾瑞网</博主><博主主页>http://weibo.com/iresearch21cn?refer_flag=1001030103_</博主主页><博文>
		【BAT三雄激战，人工智能成竞争新变量】经历近20年的发展，BAT（百度、阿里、腾讯）这三家中国最大的互联网公司巨头已经从体量、主营业务上发生了剧变。其中百度在2016年经历了巨大波折。从贴吧风波到魏则西事件，从调整百度医疗事业部到“四大金刚出走”，百度发展速度放缓。阿里巴巴和腾讯则纷纷尝试 ​
			...展开全文c
		</博文><博文独立网址>http://weibo.com/1796217437/ECcbbp3dq?refer_flag=1001030103_</博文独立网址><发布时间>2017-03-30 16:15</发布时间><发布终端>微博 weibo.com</发布终端><转发数>1</转发数><评论数/><点赞数/><EXPORTFLAG/></item><item><博主头像>http://tvax1.sinaimg.cn/default/images/default_avatar_male_50.gif</博主头像><博主id>5739122844</博主id><博主>黔灵山的猴</博主><博主主页>http://weibo.com/u/5739122844?refer_flag=1001030103_</博主主页><博文>
		发表了博文《互联网+医疗行业从现象到本质-开篇(四)》众包痛客平台ppseeker认为百度裁撤医疗事业部，却还无法杜绝“魏则西事件”而且这绝对不是为“魏则西事件”表态，而是，裁撤一个绩效极差的部门，要|互联网+医... ​
		</博文><博文独立网址>http://weibo.com/5739122844/ECbGNjI6J?refer_flag=1001030103_</博文独立网址><发布时间>2017-03-30 15:00</发布时间><发布终端>新浪博客</发布终端><转发数/><评论数/><点赞数/><EXPORTFLAG/></item><item><博主头像>http://tva4.sinaimg.cn/crop.0.0.200.200.50/005LzU0Tjw1ekn9iqsw2mj305k05kglk.jpg</博主头像><博主id>5283708751</博主id><博主>可爱猫咪heart</博主><博主主页>http://weibo.com/u/5283708751?refer_flag=1001030103_</博主主页><博文>
		魏则西百度推广事件谁以后再敢说有问题找度娘 我特么就是你干爹。  ​
		</博文><博文独立网址>http://weibo.com/5283708751/ECaMk1L5H?refer_flag=1001030103_</博文独立网址><发布时间>2017-03-30 12:41</发布时间><发布终端>微博 weibo.com</发布终端><转发数/><评论数/><点赞数/><EXPORTFLAG/></item><item><博主头像>http://tvax1.sinaimg.cn/crop.0.0.996.996.50/a4bdb7d7ly8fezdpvqceej20ro0ro77l.jpg</博主头像><博主id>2763896791</博主id><博主>艹氵已十甫寸文</博主><博主主页>http://weibo.com/u/2763896791?refer_flag=1001030103_</博主主页><博文>
		从李明远到曾良，因为反腐百度痛下杀手；从吴恩达到王劲，源自业务调整的阵痛不得不离开，再加上因“魏则西事件”引发的百度推广顽疾而背锅的王湛，百度的副总裁们命运多舛。价值兄发现，从20网页链接 ​
		</博文><博文独立网址>http://weibo.com/2763896791/ECaa7pqmc?refer_flag=1001030103_</博文独立网址><发布时间>2017-03-30 11:06</发布时间><发布终端>UC浏览器Android</发布终端><转发数/><评论数/><点赞数/><EXPORTFLAG/></item><item><博主头像>http://tvax1.sinaimg.cn/crop.0.0.996.996.50/a4bdb7d7ly8fezdpvqceej20ro0ro77l.jpg</博主头像><博主id>2763896791</博主id><博主>艹氵已十甫寸文</博主><博主主页>http://weibo.com/u/2763896791?refer_flag=1001030103_</博主主页><博文>
		从李明远到曾良，因为反腐百度痛下杀手；从吴恩达到王劲，源自业务调整的阵痛不得不离开，再加上因“魏则西事件”引发的百度推广顽疾而背锅的王湛，百度的副总裁们命运多舛。价值兄发现，从20网页链接 ​
		</博文><博文独立网址>http://weibo.com/2763896791/ECa9fjmBW?refer_flag=1001030103_</博文独立网址><发布时间>2017-03-30 11:04</发布时间><发布终端>UC浏览器Android</发布终端><转发数/><评论数/><点赞数/><EXPORTFLAG/></item><item><博主头像>http://tva3.sinaimg.cn/crop.0.0.100.100.50/0063QtsNjw8erok7s5somj302s02sgld.jpg</博主头像><博主id>5553632317</博主id><博主>蓦然回首5015</博主><博主主页>http://weibo.com/u/5553632317?refer_flag=1001030103_</博主主页><博文>
		呃，无法说。就我身边情况，父亲（家庭）信这个也许是实数没办法的办法了，有的疾病/症状/心理行为是现在医学（科学的）无法检测并对症下药的、类似魏则西事件。只能寄托于神明了吧。在现代社会，这确实实数没办法的办法。
		</博文><博文独立网址>http://weibo.com/1907166177/EC9DsBu6j?refer_flag=1001030103_</博文独立网址><发布时间>2017-03-30 10:13</发布时间><发布终端>iPhone 7 Plus</发布终端><转发数/><评论数/><点赞数/><EXPORTFLAG/></item><item><博主头像>http://tva1.sinaimg.cn/crop.0.0.200.200.50/005Foahajw8f1j7wu1qqdj305k05kjrf.jpg</博主头像><博主id>5192253312</博主id><博主>XCAR宝哥</博主><博主主页>http://weibo.com/u/5192253312?refer_flag=1001030103_</博主主页><博文>
		魏则西百度推广事件谁以后再敢说有问题找度娘 我特么就是你干爹。  ​
		</博文><博文独立网址>http://weibo.com/5192253312/EC95c5sUD?refer_flag=1001030103_</博文独立网址><发布时间>2017-03-30 08:22</发布时间><发布终端>微博 weibo.com</发布终端><转发数/><评论数/><点赞数/><EXPORTFLAG/></item></列></item></列表></extraction>