<?xml version="1.0" encoding="UTF-8"?><extraction><clueid>366830406</clueid><fullpath><![CDATA[http://s.weibo.com/weibo/%25E9%259B%2584%25E5%25AE%2589%25E6%2596%25B0%25E5%258C%25BA&typeall=1&suball=1&timescope=custom:2017-01-01:2017-05-13-23&page=22]]></fullpath><realpath><![CDATA[http://s.weibo.com/weibo/%25E9%259B%2584%25E5%25AE%2589%25E6%2596%25B0%25E5%258C%25BA&typeall=1&suball=1&timescope=custom:2017-01-01:2017-05-13-23&page=22]]></realpath><theme>微博关键词搜索采集</theme><middle>default</middle><createdate>2017-5-13 15:21:7</createdate><pageno>21</pageno><actionno></actionno><actionvalue></actionvalue><prestamp>DSEngine-+-ds_browser_ds_task_xp1-+-11428681</prestamp><currentstamp>DSEngine-+-ds_browser_ds_task_xp1-+-11448149</currentstamp><baseURI><bucketBaseURI><bucketName>list</bucketName><uri><![CDATA[http://s.weibo.com/weibo/%25E9%259B%2584%25E5%25AE%2589%25E6%2596%25B0%25E5%258C%25BA&typeall=1&suball=1&timescope=custom:2017-01-01:2017-05-13-23&page=22]]></uri></bucketBaseURI></baseURI>
<列表><item><关键字>雄安新区</关键字><列><item><博主头像>http://tva1.sinaimg.cn/crop.13.1.158.158.50/006w1u4Jjw8f5924paawcj305804g3yf.jpg</博主头像><博主id>5969993685</博主id><博主>laoduo666</博主><博主主页>http://weibo.com/laoduo666?refer_flag=1001030103_</博主主页><博文>
		发布了头条文章：《市场终于正常了》 #投资达人说# #今日看盘# #财经头条文章# #微博股票# #雄安新区# #午盘聚焦# $冀东装备 sz000856$ $北新路桥 sz002307$ |市场终于正... ​
		</博文><博文独立网址>http://weibo.com/5969993685/F1o1tpO9r?refer_flag=1001030103_</博文独立网址><发布时间>2017-05-03 13:07</发布时间><发布终端>微博 weibo.com</发布终端><转发数>8</转发数><评论数>9</评论数><点赞数>76</点赞数><EXPORTFLAG/></item><item><博主头像>http://tva3.sinaimg.cn/crop.0.0.996.996.50/693615cfjw8fc7xdwxsspj20ro0rpwgt.jpg</博主头像><博主id>1765152207</博主id><博主>橘子-烊光-向日葵</博主><博主主页>http://weibo.com/boboaigeng?refer_flag=1001030103_</博主主页><博文>
		想去买个楼。。可是没钱
		</博文><博文独立网址>http://weibo.com/1618051664/F1nYpoVE1?refer_flag=1001030103_</博文独立网址><发布时间>2017-05-03 13:06</发布时间><发布终端>微博 weibo.com</发布终端><转发数/><评论数/><点赞数/><EXPORTFLAG/></item><item><博主头像>http://tva3.sinaimg.cn/crop.0.0.996.996.50/3c38a861jw8fayqf6e2suj20ro0roadz.jpg</博主头像><博主id>1010346081</博主id><博主>Jiyeon_Julian</博主><博主主页>http://weibo.com/u/1010346081?refer_flag=1001030103_</博主主页><博文>
		雄安家中坐，财神上门来。
		</博文><博文独立网址>http://weibo.com/1618051664/F1nYpoVE1?refer_flag=1001030103_</博文独立网址><发布时间>2017-05-03 13:06</发布时间><发布终端>微博 weibo.com</发布终端><转发数/><评论数/><点赞数/><EXPORTFLAG/></item><item><博主头像>http://tva1.sinaimg.cn/crop.0.0.491.491.50/7e1b1c10jw8fcuybh5ahij20dw0dw75h.jpg</博主头像><博主id>2115705872</博主id><博主>美仁尖</博主><博主主页>http://weibo.com/u/2115705872?refer_flag=1001030103_</博主主页><博文>
		讲真，真心觉得讽刺，get不到点
		</博文><博文独立网址>http://weibo.com/1618051664/F1nYpoVE1?refer_flag=1001030103_</博文独立网址><发布时间>2017-05-03 13:05</发布时间><发布终端>微博 weibo.com</发布终端><转发数/><评论数/><点赞数/><EXPORTFLAG/></item><item><博主头像>http://tva1.sinaimg.cn/crop.0.0.1241.1241.50/005IXJSIjw8ez6dt9q9q7j30yi0yhgpz.jpg</博主头像><博主id>5245060668</博主id><博主>远旸新闻</博主><博主主页>http://weibo.com/u/5245060668?refer_flag=1001030103_</博主主页><博文>
		如何变怎么变
		</博文><博文独立网址>http://weibo.com/1618051664/F1nYpoVE1?refer_flag=1001030103_</博文独立网址><发布时间>2017-05-03 13:01</发布时间><发布终端>微博 weibo.com</发布终端><转发数/><评论数/><点赞数/><EXPORTFLAG/></item><item><博主头像>http://tvax2.sinaimg.cn/crop.18.21.500.500.50/60718250ly1fe7kog3jroj20f00f03zj.jpg</博主头像><博主id>1618051664</博主id><博主>头条新闻</博主><博主主页>http://weibo.com/breakingnews?refer_flag=1001030103_</博主主页><博文>
		#新浪看见#【雄安新区满月：雄安梦想家】34岁的雄县人刘伟时常感叹青春已逝，而县城生活却一成不变。然而自从雄安新区成立以来，他突然感到一场巨变即将来临。新浪摄影师记录了雄安当地6位年轻人的故事，他们有的从未离开，有的在外闯荡又回来，对未来有焦虑也有期待。|雄安梦想家 ​
		</博文><博文独立网址>http://weibo.com/1618051664/F1nYpoVE1?refer_flag=1001030103_</博文独立网址><发布时间>2017-05-03 12:59</发布时间><发布终端>微博 weibo.com</发布终端><转发数>91</转发数><评论数>274</评论数><点赞数>267</点赞数><EXPORTFLAG/></item><item><博主头像>http://tva3.sinaimg.cn/crop.0.0.664.664.50/3c2bfbe4jw8ez89hdqjasj20ig0ig3z6.jpg</博主头像><博主id>1009515492</博主id><博主>闫大夫聊肝病</博主><博主主页>http://weibo.com/dryanjie?refer_flag=1001030103_</博主主页><博文>
		这个好像耳熟啊——楼上楼下，电灯电话
		</博文><博文独立网址>http://weibo.com/1889213710/EEmQctwcR?refer_flag=1001030103_</博文独立网址><发布时间>2017-05-03 12:57</发布时间><发布终端>微博 weibo.com</发布终端><转发数/><评论数>4</评论数><点赞数>1</点赞数><EXPORTFLAG/></item><item><博主头像>http://tva4.sinaimg.cn/crop.0.0.180.180.50/5399fdfajw1e8qgp5bmzyj2050050aa8.jpg</博主头像><博主id>1402600954</博主id><博主>睿睿霸</博主><博主主页>http://weibo.com/saystrangeto?refer_flag=1001030103_</博主主页><博文>
		计划经济试点//@刘胜军改革:经与河北省和雄安新区共同研究，国土资源部计划将雄安新区作为国土资源管理改革试点和创新政策的先行先试区，重点从保障用地需求、土地供应政策、城市地质调查、不动产统一登记和土地税费相关政策等方面给予支持。
		</博文><博文独立网址>http://weibo.com/1889213710/EEmQctwcR?refer_flag=1001030103_</博文独立网址><发布时间>2017-05-03 12:52</发布时间><发布终端>微博 weibo.com</发布终端><转发数/><评论数/><点赞数/><EXPORTFLAG/></item><item><博主头像>http://tva2.sinaimg.cn/crop.43.279.559.559.50/dbe4abc5gw1f6dgk5c3puj20j60pwdke.jpg</博主头像><博主id>3689196485</博主id><博主>广州市刘俊</博主><博主主页>http://weibo.com/lj48799?refer_flag=1001030103_</博主主页><博文>
		在微信朋友圈闲聊“猜测雄安新区城市中心区可能在白洋淀边非生态保护区的某处适宜建城的地方”的文字截屏 ​​​
		</博文><博文独立网址>http://weibo.com/3689196485/F1nLJ8ndG?refer_flag=1001030103_</博文独立网址><发布时间>2017-05-03 12:28</发布时间><发布终端>红米Note 3</发布终端><转发数/><评论数/><点赞数/><EXPORTFLAG/></item><item><博主头像>http://tvax1.sinaimg.cn/crop.0.0.1006.1006.50/006bRceJly8ff5x3ao1u1j30ry0rywlo.jpg</博主头像><博主id>5672015113</博主id><博主>拜拜皮卡丘</博主><博主主页>http://weibo.com/u/5672015113?refer_flag=1001030103_</博主主页><博文>
		以后我大安新将变成雄安，再也找不到水边烧烤的赶脚#秦皇岛·北戴河区[地点]#
		</博文><博文独立网址>http://weibo.com/6193114113/F14SgD8za?refer_flag=1001030103_</博文独立网址><发布时间>2017-05-03 12:23</发布时间><发布终端>秒拍网页版</发布终端><转发数/><评论数>3</评论数><点赞数/><EXPORTFLAG/></item><item><博主头像>http://tvax1.sinaimg.cn/crop.68.0.1974.1974.50/713c0483ly1fdt0tih6jyj21kw1kwai0.jpg</博主头像><博主id>1899758723</博主id><博主>村网通漯河</博主><博主主页>http://weibo.com/0395jfl?refer_flag=1001030103_</博主主页><博文>
		万亿级管廊建设进入爆发期，雄安新区投资额巨大_河南省漯河市召陵区万金镇-乡镇之家【全国乡镇通工程】 网页链接 ​
		</博文><博文独立网址>http://weibo.com/1899758723/F1nJIoyDf?refer_flag=1001030103_</博文独立网址><发布时间>2017-05-03 12:23</发布时间><发布终端>百度分享</发布终端><转发数/><评论数/><点赞数>1</点赞数><EXPORTFLAG/></item><item><博主头像>http://tva4.sinaimg.cn/crop.59.164.351.351.50/709b1d0ejw1e98bbrprmij20c80ga40v.jpg</博主头像><博主id>1889213710</博主id><博主>刘胜军改革</博主><博主主页>http://weibo.com/u/1889213710?refer_flag=1001030103_</博主主页><博文>
		经与河北省和雄安新区共同研究，国土资源部计划将雄安新区作为国土资源管理改革试点和创新政策的先行先试区，重点从保障用地需求、土地供应政策、城市地质调查、不动产统一登记和土地税费相关政策等方面给予支持。 
		</博文><博文独立网址>http://weibo.com/1889213710/EEmQctwcR?refer_flag=1001030103_</博文独立网址><发布时间>2017-05-03 12:18</发布时间><发布终端>微博 weibo.com</发布终端><转发数>11</转发数><评论数>6</评论数><点赞数>5</点赞数><EXPORTFLAG/></item><item><博主头像>http://tvax1.sinaimg.cn/crop.10.0.492.492.50/005UN6F5ly8ff4kl5hc0nj30e80dojru.jpg</博主头像><博主id>5419842659</博主id><博主>汪小让</博主><博主主页>http://weibo.com/u/5419842659?refer_flag=1001030103_</博主主页><博文>
		进军雄安新区
		</博文><博文独立网址>http://weibo.com/1642088277/F1mgf1X5y?refer_flag=1001030103_</博文独立网址><发布时间>2017-05-03 11:55</发布时间><发布终端>微博 weibo.com</发布终端><转发数/><评论数/><点赞数/><EXPORTFLAG/></item><item><博主头像>http://tva2.sinaimg.cn/crop.2.0.1242.1242.50/006pvdvqjw8fcbx095lk9j30yn0yiq5f.jpg</博主头像><博主id>5873645480</博主id><博主>股民-张敬宇</博主><博主主页>http://weibo.com/u/5873645480?refer_flag=1001030103_</博主主页><博文>
		不含ST板块，两市有近44只个股涨停，9只个股跌停。石家庄将申报正定国家级新区，承接非首都功能疏解， 常山药业两连板， 远达环保涨停。开板次新崛起， 坤彩科技涨停。 一带一路高峰论坛渐近，八一钢铁、 兰石重装和 天山股份涨停。雄安新区分化， 津膜科技、 韩建河山和 汉钟精机涨停， 庞大集团跌停 ​
			...展开全文c
		</博文><博文独立网址>http://weibo.com/5873645480/F1nwLAj62?refer_flag=1001030103_</博文独立网址><发布时间>2017-05-03 11:51</发布时间><发布终端>iPhone 6 Plus</发布终端><转发数/><评论数>2</评论数><点赞数/><EXPORTFLAG/></item><item><博主头像>http://tvax2.sinaimg.cn/default/images/default_avatar_female_50.gif</博主头像><博主id>5871560429</博主id><博主>金蛇舞阳</博主><博主主页>http://weibo.com/u/5871560429?refer_flag=1001030103_</博主主页><博文>
		期待雄安新景象。
		</博文><博文独立网址>http://weibo.com/5094103156/F1nhabbmW?refer_flag=1001030103_</博文独立网址><发布时间>2017-05-03 11:45</发布时间><发布终端>微博 weibo.com</发布终端><转发数/><评论数/><点赞数/><EXPORTFLAG/></item><item><博主头像>http://tva3.sinaimg.cn/crop.0.0.996.996.50/006IVb6wjw8fd6yjsqm2jj30ro0rota6.jpg</博主头像><博主id>6160583160</博主id><博主>团长说房</博主><博主主页>http://weibo.com/u/6160583160?refer_flag=1001030103_</博主主页><博文>
		涿州好着呢！//@首都一片小绿叶:涿州尴尬了
		</博文><博文独立网址>http://weibo.com/6160583160/F1mn6AE2K?refer_flag=1001030103_</博文独立网址><发布时间>2017-05-03 11:39</发布时间><发布终端>HUAWEI Mate 9</发布终端><转发数>1</转发数><评论数>2</评论数><点赞数/><EXPORTFLAG/></item><item><博主头像>http://tvax3.sinaimg.cn/default/images/default_avatar_male_50.gif</博主头像><博主id>2850655850</博主id><博主>期待的日子乐悠悠</博主><博主主页>http://weibo.com/u/2850655850?refer_flag=1001030103_</博主主页><博文>
		发表了博文《5.3午评》热点方面：雄安新区分化，津膜科技，嘉寓股份，韩建河山继续保持领涨，目前不是追了；新疆股，北新路桥，八一钢铁，天山股份涨停，环保股也分化，|5.3午评 ​
		</博文><博文独立网址>http://weibo.com/2850655850/F1nrgxogB?refer_flag=1001030103_</博文独立网址><发布时间>2017-05-03 11:37</发布时间><发布终端>新浪博客</发布终端><转发数/><评论数/><点赞数/><EXPORTFLAG/></item><item><博主头像>http://tva4.sinaimg.cn/crop.0.0.180.180.50/b6974893jw1e8qgp5bmzyj2050050aa8.jpg</博主头像><博主id>3063367827</博主id><博主>世界企业家研究院</博主><博主主页>http://weibo.com/u/3063367827?refer_flag=1001030103_</博主主页><博文>
		『万亿级管廊建设进入爆发期，雄安新区投资额巨大_第一财经』|万亿级管廊... ​
		</博文><博文独立网址>http://weibo.com/3063367827/F1npTswfs?refer_flag=1001030103_</博文独立网址><发布时间>2017-05-03 11:34</发布时间><发布终端>红米Note 4G</发布终端><转发数/><评论数/><点赞数/><EXPORTFLAG/></item><item><博主头像>http://tva2.sinaimg.cn/crop.0.0.664.664.50/83a382b7jw8far4bb2y7aj20ig0ig0ug.jpg</博主头像><博主id>2208531127</博主id><博主>板栗哥大兴兴</博主><博主主页>http://weibo.com/chnqs?refer_flag=1001030103_</博主主页><博文>
		#冀语雄安新区# 相信雄安新区能够建立起来，形成京津雄三足鼎立，辐射河北省周边地区，带动整个河北省全方位发展。 ​
		</博文><博文独立网址>http://weibo.com/2208531127/F1nnFwl4r?refer_flag=1001030103_</博文独立网址><发布时间>2017-05-03 11:29</发布时间><发布终端>微话题</发布终端><转发数>3</转发数><评论数>2</评论数><点赞数>2</点赞数><EXPORTFLAG/></item><item><博主头像>http://tvax4.sinaimg.cn/default/images/default_avatar_male_50.gif</博主头像><博主id>5156091999</博主id><博主>浮冰38405</博主><博主主页>http://weibo.com/u/5156091999?refer_flag=1001030103_</博主主页><博文>
		5.1三天，省公安厅、保定市公安局驻雄安新区联合工作组及雄安新区三县公安机关1000余名民警、辅警放弃休假，坚守岗位，全面开展了交通疏导、秩序维护、巡逻防控、隐患排查、打击整治等各项工作。 ​
		</博文><博文独立网址>http://weibo.com/5156091999/F1nmQmtXr?refer_flag=1001030103_</博文独立网址><发布时间>2017-05-03 11:27</发布时间><发布终端>微博 weibo.com</发布终端><转发数/><评论数/><点赞数/><EXPORTFLAG/></item></列></item></列表></extraction>