<?xml version="1.0" encoding="UTF-8"?><extraction><clueid>33272405</clueid><fullpath><![CDATA[http://weibo.com/p/100808f26253663e38cf7c840c201a78797dde?pids=Pl_Third_App__11&current_page=9&since_id=%7B%22last_since_id%22%3A4106936180209090%2C%22res_type%22%3A1%2C%22next_since_id%22%3A4106935764922855%7D&page=4#Pl_Third_App__11]]></fullpath><realpath><![CDATA[http://weibo.com/p/100808f26253663e38cf7c840c201a78797dde?current_page=9&since_id={%22last_since_id%22%3A4106936180209090%2C%22res_type%22%3A1%2C%22next_since_id%22%3A4106935764922855}&page=4#Pl_Third_App__11]]></realpath><theme>微博话题采集</theme><middle>default</middle><createdate>2017-5-13 13:45:36</createdate><pageno>3</pageno><actionno></actionno><actionvalue></actionvalue><prestamp>DSEngine-+-ds_browser_ds_task_xp2-+-5666131</prestamp><currentstamp>DSEngine-+-ds_browser_ds_task_xp2-+-5717822</currentstamp><baseURI><bucketBaseURI><bucketName>微博话题</bucketName><uri><![CDATA[http://weibo.com/p/100808f26253663e38cf7c840c201a78797dde?current_page=9&since_id={%22last_since_id%22%3A4106936180209090%2C%22res_type%22%3A1%2C%22next_since_id%22%3A4106935764922855}&page=4#Pl_Third_App__11]]></uri></bucketBaseURI></baseURI>
<微博话题><item><话题>#母亲节#</话题><导语>
				导语：成为妈妈或许让你感到光芒不再，但来自孩子和另一半的爱却能帮助你找回自信。今年的母亲节，OLAY祝福所有的妈妈母亲节快乐，快来分享出你的另一半和孩子做过的最感动你的事吧，OLAY将挑选出十五位妈妈，送出OLAY的新生好礼。
			</导语><阅读数>24.4亿</阅读数><讨论数>933.7万</讨论数><粉丝数>2.3万</粉丝数><列><item><样例><item><博主>OLAY</博主><博主id>1645365377</博主id><博主主页>http://weibo.com/olay?refer_flag=1008085010_</博主主页><博主头像>http://tvax3.sinaimg.cn/crop.0.0.180.180.50/62124881ly8fe51dv0y2zj2050050aa0.jpg</博主头像><博文>置顶                                                    成为妈妈，却感觉失去光芒，自信不再？但另一半的爱却能让你重拾美好，相信现在就是自己最美的时刻。#母亲节#期间，转发微博分享出你的另一半或宝贝为你做过最感人的事，将有15位妈妈赢得OLAY送出的冻龄好礼。与OLAY一起，为妈妈点亮肌肤光芒，让她在最美好的时光里无惧年龄！ L母亲节最好的礼物 ​​​​                                            </博文><博文独立网址>http://weibo.com/1645365377/F1AWG1FNM</博文独立网址><发布时间>2017-05-04 22:01</发布时间><发布终端>微博 weibo.com</发布终端><转发数> 13322</转发数><评论数> 2370</评论数><点赞数>13591</点赞数><转发_博主/><转发_博主id/><转发_博主主页/><转发_博文/><转发_发布时间/><转发_发布终端/><转发_转发数/><转发_评论数/><转发_点赞数/><EXPORTFLAG/></item><item><博主>笙南</博主><博主id>3766773034</博主id><博主主页>http://weibo.com/u/3766773034?refer_flag=1008085010_</博主主页><博主头像>http://tva3.sinaimg.cn/crop.0.0.1242.1242.50/e084652ajw8f2hj7kztoxj20yi0yijsd.jpg</博主头像><博文>置顶                                                    “从小觉得最厉害的人就是妈妈，不怕黑，什么都知道，做好吃的饭，把生活打理得井井有条，哭着不知道怎么办时只好找她。可我好像忘了这个被我依靠的人也曾是个小姑娘，怕黑也掉眼泪，笨手笨脚会被针扎到手。最美的姑娘，是什么让你变得这么强大呢，是岁月，还是爱。无惧年龄，老妈不老。” ​​​​...展开全文c                                            </博文><博文独立网址>http://weibo.com/3766773034/F2rhlyBgG</博文独立网址><发布时间>2017-05-10 11:14</发布时间><发布终端>iPhone 6s Plus</发布终端><转发数> 1367</转发数><评论数> 212</评论数><点赞数>1794</点赞数><转发_博主/><转发_博主id/><转发_博主主页/><转发_博文/><转发_发布时间/><转发_发布终端/><转发_转发数/><转发_评论数/><转发_点赞数/><EXPORTFLAG/></item></样例></item><item><样例><item><博主>万亚琴_23131</博主><博主id>3551751880</博主id><博主主页>http://weibo.com/u/3551751880?refer_flag=1008085010_</博主主页><博主头像>http://tva3.sinaimg.cn/crop.0.0.664.664.50/d3b36ec8jw8f3bk96952uj20ig0ig0u2.jpg</博主头像><博文>                                                    #母亲节# 晒成煤球了 2岳阳·奇家岭 ​​​​                                            </博文><博文独立网址>http://weibo.com/3551751880/F2UqGfexu</博文独立网址><发布时间>2017-05-13 13:27</发布时间><发布终端>OPPO R9s</发布终端><转发数>转发</转发数><评论数>评论</评论数><点赞数>赞</点赞数><转发_博主/><转发_博主id/><转发_博主主页/><转发_博文/><转发_发布时间/><转发_发布终端/><转发_转发数/><转发_评论数/><转发_点赞数/><EXPORTFLAG/></item><item><博主>老衲只用飘柔marlboro</博主><博主id>2993731641</博主id><博主主页>http://weibo.com/u/2993731641?refer_flag=1008085010_</博主主页><博主头像>http://tva3.sinaimg.cn/crop.0.0.996.996.50/b270b839jw8f9gcza3z05j20ro0rowhj.jpg</博主头像><博文>                                                    这是我这辈子.住过的最贵的房子 ，最安全的房子！也是我这一生都无法交清的房贷 ，祝天下所有的妈妈节日快乐，永远健康长寿！#母亲节##母亲节快乐# 2成都·香格里拉大酒店 ​​​​                                            </博文><博文独立网址>http://weibo.com/2993731641/F2UqBwijK</博文独立网址><发布时间>2017-05-13 13:27</发布时间><发布终端>OPPO R9</发布终端><转发数>转发</转发数><评论数>评论</评论数><点赞数>3</点赞数><转发_博主/><转发_博主id/><转发_博主主页/><转发_博文/><转发_发布时间/><转发_发布终端/><转发_转发数/><转发_评论数/><转发_点赞数/><EXPORTFLAG/></item><item><博主>看海人</博主><博主id>1652173897</博主id><博主主页>http://weibo.com/206000345?refer_flag=1008085010_</博主主页><博主头像>http://tva1.sinaimg.cn/crop.237.0.666.666.50/627a2c49gw1eefdyjmrp3j20ru0ikwj3.jpg</博主头像><博文>                                                    “世上只有麻麻好！#感恩母亲节##母亲节#”L看海人的秒拍视频 (使用#秒拍#录制,免流量看热门短视频!) ​​​​                                            </博文><博文独立网址>http://weibo.com/1652173897/F2Uqma1J8</博文独立网址><发布时间>2017-05-13 13:26</发布时间><发布终端>秒拍客户端</发布终端><转发数>转发</转发数><评论数>评论</评论数><点赞数>2</点赞数><转发_博主/><转发_博主id/><转发_博主主页/><转发_博文/><转发_发布时间/><转发_发布终端/><转发_转发数/><转发_评论数/><转发_点赞数/><EXPORTFLAG/></item><item><博主>KIDSING儿童潮牌</博主><博主id>6014853960</博主id><博主主页>http://weibo.com/u/6014853960?refer_flag=1008085010_</博主主页><博主头像>http://tva4.sinaimg.cn/crop.0.0.620.620.50/006z3Ihyjw8f83c8krscfj30hs0hs3zn.jpg</博主头像><博文>                                                    感恩，祝天下的麻麻，节日快乐！辛苦了#母亲节# ​​​​                                            </博文><博文独立网址>http://weibo.com/6014853960/F2UqjcA5R</博文独立网址><发布时间>2017-05-13 13:26</发布时间><发布终端>360安全浏览器</发布终端><转发数>转发</转发数><评论数>评论</评论数><点赞数>赞</点赞数><转发_博主/><转发_博主id/><转发_博主主页/><转发_博文/><转发_发布时间/><转发_发布终端/><转发_转发数/><转发_评论数/><转发_点赞数/><EXPORTFLAG/></item><item><博主>大家都叫我小红</博主><博主id>5060776995</博主id><博主主页>http://weibo.com/u/5060776995?refer_flag=1008085010_</博主主页><博主头像>http://tvax2.sinaimg.cn/crop.0.21.1242.1242.50/005wuvhply8ffd56qdrx3j30yi0zpdic.jpg</博主头像><博文>                                                    #母亲节# ​​​​                                            </博文><博文独立网址>http://weibo.com/5060776995/F2Uqiino6</博文独立网址><发布时间>2017-05-13 13:26</发布时间><发布终端>iPhone 6s Plus</发布终端><转发数>转发</转发数><评论数>评论</评论数><点赞数>赞</点赞数><转发_博主/><转发_博主id/><转发_博主主页/><转发_博文/><转发_发布时间/><转发_发布终端/><转发_转发数/><转发_评论数/><转发_点赞数/><EXPORTFLAG/></item><item><博主>用户5741786133</博主><博主id>5741786133</博主id><博主主页>http://weibo.com/u/5741786133?refer_flag=1008085010_</博主主页><博主头像>http://tva2.sinaimg.cn/crop.0.0.996.996.50/006gzWRLjw8fckol3uc21j30ro0rpdjt.jpg</博主头像><博文>                                                    #母亲节#给妈妈做的午餐 ​​​​                                            </博文><博文独立网址>http://weibo.com/5741786133/F2Uqh7tMw</博文独立网址><发布时间>2017-05-13 13:26</发布时间><发布终端>荣耀6 Plus</发布终端><转发数>转发</转发数><评论数>评论</评论数><点赞数>赞</点赞数><转发_博主/><转发_博主id/><转发_博主主页/><转发_博文/><转发_发布时间/><转发_发布终端/><转发_转发数/><转发_评论数/><转发_点赞数/><EXPORTFLAG/></item><item><博主>BDSM201704</博主><博主id>6228286686</博主id><博主主页>http://weibo.com/u/6228286686?refer_flag=1008085010_</博主主页><博主头像>http://tvax3.sinaimg.cn/crop.0.0.664.664.50/006NvfSSly8ff1cff4yl5j30ig0igmyf.jpg</博主头像><博文>                                                    #母亲节# ​​​​                                            </博文><博文独立网址>http://weibo.com/6228286686/F2UqesA0Q</博文独立网址><发布时间>2017-05-13 13:26</发布时间><发布终端>Android客户端</发布终端><转发数>转发</转发数><评论数>评论</评论数><点赞数>赞</点赞数><转发_博主/><转发_博主id/><转发_博主主页/><转发_博文/><转发_发布时间/><转发_发布终端/><转发_转发数/><转发_评论数/><转发_点赞数/><EXPORTFLAG/></item><item><博主>hey-翘翘</博主><博主id>3057022563</博主id><博主主页>http://weibo.com/u/3057022563?refer_flag=1008085010_</博主主页><博主头像>http://tva4.sinaimg.cn/crop.0.0.750.750.50/b6367663jw8f1qbv1ftsvj20ku0ku0u7.jpg</博主头像><博文>                                                    #全世界最美丽的人##母亲节# 是你让我每一年又多了一个节日 2平顶山 ​​​​                                            </博文><博文独立网址>http://weibo.com/3057022563/F2Uqcnr13</博文独立网址><发布时间>2017-05-13 13:26</发布时间><发布终端>iPhone 6s</发布终端><转发数>转发</转发数><评论数>评论</评论数><点赞数>赞</点赞数><转发_博主/><转发_博主id/><转发_博主主页/><转发_博文/><转发_发布时间/><转发_发布终端/><转发_转发数/><转发_评论数/><转发_点赞数/><EXPORTFLAG/></item><item><博主>鹿地现场</博主><博主id>6110493538</博主id><博主主页>http://weibo.com/u/6110493538?refer_flag=1008085010_</博主主页><博主头像>http://tva3.sinaimg.cn/crop.0.0.2048.2048.50/006Fx0vojw8fcj3t3qehxj31kw1kwn33.jpg</博主头像><博文>                                                    #鹿地现场# 母亲节，来听一首温暖的歌~这个#母亲节# 记得跟妈妈说一声"节日快乐"别让她等太久~ L秒拍视频 ​​​​                                            </博文><博文独立网址>http://weibo.com/6110493538/F2Uqamtx4</博文独立网址><发布时间>2017-05-13 13:26</发布时间><发布终端>小米手机5</发布终端><转发数>转发</转发数><评论数> 1</评论数><点赞数>1</点赞数><转发_博主/><转发_博主id/><转发_博主主页/><转发_博文/><转发_发布时间/><转发_发布终端/><转发_转发数/><转发_评论数/><转发_点赞数/><EXPORTFLAG/></item><item><博主>用户6201807531</博主><博主id>6201807531</博主id><博主主页>http://weibo.com/u/6201807531?refer_flag=1008085010_</博主主页><博主头像>http://tvax3.sinaimg.cn/crop.0.0.640.640.50/006LI9rJly8fejj9ri6n4j30hs0hst9l.jpg</博主头像><博文>                                                    #母亲节# ​​​​                                            </博文><博文独立网址>http://weibo.com/6201807531/F2Uq9bnQQ</博文独立网址><发布时间>2017-05-13 13:26</发布时间><发布终端>iPhone客户端</发布终端><转发数>转发</转发数><评论数>评论</评论数><点赞数>1</点赞数><转发_博主/><转发_博主id/><转发_博主主页/><转发_博文/><转发_发布时间/><转发_发布终端/><转发_转发数/><转发_评论数/><转发_点赞数/><EXPORTFLAG/></item><item><博主>青岛熙珠韩装服饰有限公司</博主><博主id>5816245717</博主id><博主主页>http://weibo.com/qdsilvedew?refer_flag=1008085010_</博主主页><博主头像>http://tva2.sinaimg.cn/crop.0.0.638.638.50/006lCncNjw8f9g48anmy6j30hq0hq3z2.jpg</博主头像><博文>                                                    #母亲节# ​​​​                                            </博文><博文独立网址>http://weibo.com/5816245717/F2Uq3w8kN</博文独立网址><发布时间>2017-05-13 13:25</发布时间><发布终端>微话题-母亲节</发布终端><转发数>转发</转发数><评论数>评论</评论数><点赞数>赞</点赞数><转发_博主/><转发_博主id/><转发_博主主页/><转发_博文/><转发_发布时间/><转发_发布终端/><转发_转发数/><转发_评论数/><转发_点赞数/><EXPORTFLAG/></item><item><博主>Purple_Pie</博主><博主id>2589967544</博主id><博主主页>http://weibo.com/u/2589967544?refer_flag=1008085010_</博主主页><博主头像>http://tva4.sinaimg.cn/crop.0.3.750.750.50/9a5fc4b8jw8fcsggc0m79j20ku0l0js8.jpg</博主头像><博文>                                                    #母亲节# ​​​​                                            </博文><博文独立网址>http://weibo.com/2589967544/F2PUxuCJO</博文独立网址><发布时间>2017-05-13 01:57</发布时间><发布终端>iPhone 7</发布终端><转发数>转发</转发数><评论数> 2</评论数><点赞数>赞</点赞数><转发_博主/><转发_博主id/><转发_博主主页/><转发_博文/><转发_发布时间/><转发_发布终端/><转发_转发数/><转发_评论数/><转发_点赞数/><EXPORTFLAG/></item><item><博主>莹莹莹莹莹莹陳</博主><博主id>5168693873</博主id><博主主页>http://weibo.com/u/5168693873?refer_flag=1008085010_</博主主页><博主头像>http://tvax2.sinaimg.cn/crop.0.9.1242.1242.50/005DNjodly8ff7j5m0aqqj30yi0z00wb.jpg</博主头像><博文>                                                    #母亲节# ​​​​                                            </博文><博文独立网址>http://weibo.com/5168693873/F2Uq2jV9U</博文独立网址><发布时间>2017-05-13 13:25</发布时间><发布终端>iPhone</发布终端><转发数>转发</转发数><评论数>评论</评论数><点赞数>赞</点赞数><转发_博主/><转发_博主id/><转发_博主主页/><转发_博文/><转发_发布时间/><转发_发布终端/><转发_转发数/><转发_评论数/><转发_点赞数/><EXPORTFLAG/></item><item><博主>wSs_Hey</博主><博主id>1102588113</博主id><博主主页>http://weibo.com/u/1102588113?refer_flag=1008085010_</博主主页><博主头像>http://tvax3.sinaimg.cn/crop.0.0.512.512.50/41b828d1ly8fex4bdz5bqj20e80e8jrg.jpg</博主头像><博文>                                                    #母亲节# ​​​​                                            </博文><博文独立网址>http://weibo.com/1102588113/F2Uq1bZWm</博文独立网址><发布时间>2017-05-13 13:25</发布时间><发布终端>iPhone 7 Plus</发布终端><转发数>转发</转发数><评论数>评论</评论数><点赞数>赞</点赞数><转发_博主/><转发_博主id/><转发_博主主页/><转发_博文/><转发_发布时间/><转发_发布终端/><转发_转发数/><转发_评论数/><转发_点赞数/><EXPORTFLAG/></item><item><博主>美丽灯夜</博主><博主id>1377261661</博主id><博主主页>http://weibo.com/maodunxin?refer_flag=1008085010_</博主主页><博主头像>http://tva3.sinaimg.cn/crop.0.0.180.180.50/5217585djw1e8qgp5bmzyj2050050aa8.jpg</博主头像><博文>                                                    老公买回来的两个大榴莲，说是专门给我买的，以庆祝明天的母亲节。好了，虽然这么大，吃完它很发愁，但很感谢老公的这番心意。#母亲节# ​​​​                                            </博文><博文独立网址>http://weibo.com/1377261661/F2UpP27Aj</博文独立网址><发布时间>2017-05-13 13:25</发布时间><发布终端>华为P9手机摄影再突破</发布终端><转发数>转发</转发数><评论数>评论</评论数><点赞数>赞</点赞数><转发_博主/><转发_博主id/><转发_博主主页/><转发_博文/><转发_发布时间/><转发_发布终端/><转发_转发数/><转发_评论数/><转发_点赞数/><EXPORTFLAG/></item><item><博主>漫粉1980</博主><博主id>3189779461</博主id><博主主页>http://weibo.com/u/3189779461?refer_flag=1008085010_</博主主页><博主头像>http://tva4.sinaimg.cn/crop.0.0.718.718.50/be202c05jw8ehtsjw6cpfj20jy0jzq5s.jpg</博主头像><博文>                                                    现在只用➕11美金就可以得到一盒敏动力哦！#母亲节##我手机里的你# ​​​​                                            </博文><博文独立网址>http://weibo.com/3189779461/F2UpOrcuQ</博文独立网址><发布时间>2017-05-13 13:25</发布时间><发布终端>iPhone 6 Plus</发布终端><转发数>转发</转发数><评论数>评论</评论数><点赞数>赞</点赞数><转发_博主/><转发_博主id/><转发_博主主页/><转发_博文/><转发_发布时间/><转发_发布终端/><转发_转发数/><转发_评论数/><转发_点赞数/><EXPORTFLAG/></item><item><博主>叶绿体81</博主><博主id>1840811515</博主id><博主主页>http://weibo.com/u/1840811515?refer_flag=1008085010_</博主主页><博主头像>http://tva3.sinaimg.cn/crop.0.0.180.180.50/6db88dfbjw1e8qgp5bmzyj2050050aa8.jpg</博主头像><博文>                                                    0-3岁是孩子性格培养最关键的时期。这个时间段孩子每天接触的人对孩子的影响至关重要。我要替这小孩感谢他有一个乐观开朗每天爱笑的姥姥，三岁前感谢姥姥的陪伴和每天的笑容。明天是母亲节。祝妈妈每天快乐#母亲节# ​​​​                                            </博文><博文独立网址>http://weibo.com/1840811515/F2Upeay0Q</博文独立网址><发布时间>2017-05-13 13:23</发布时间><发布终端>iPhone 6s</发布终端><转发数>转发</转发数><评论数>评论</评论数><点赞数>赞</点赞数><转发_博主/><转发_博主id/><转发_博主主页/><转发_博文/><转发_发布时间/><转发_发布终端/><转发_转发数/><转发_评论数/><转发_点赞数/><EXPORTFLAG/></item></样例></item></列></item></微博话题></extraction>